alignak_module_nsca/__init__.py
alignak_module_nsca/nsca.py
alignak_module_nsca/etc/__init__.py
alignak_module_nsca/etc/alignak.d/alignak-module-nsca.ini
alignak_module_nsca/etc/arbiter/modules/mod-nsca.cfg
alignak_module_nsca-2.0.0.data/data/share/alignak/etc/alignak.d/alignak-module-nsca.ini
alignak_module_nsca-2.0.0.data/data/share/alignak/etc/arbiter/modules/mod-nsca.cfg
alignak_module_nsca-2.0.0.dist-info/METADATA
alignak_module_nsca-2.0.0.dist-info/RECORD
alignak_module_nsca-2.0.0.dist-info/WHEEL
alignak_module_nsca-2.0.0.dist-info/top_level.txt
test/__init__.py
test/alignak_test.py
test/test_module.py
